gigadoom/__init__.py
gigadoom/chat.py
gigadoom-0.0.1.dist-info/LICENSE
gigadoom-0.0.1.dist-info/METADATA
gigadoom-0.0.1.dist-info/WHEEL
gigadoom-0.0.1.dist-info/top_level.txt
gigadoom-0.0.1.dist-info/RECORD
