Metadata-Version: 2.1
Name: gigadoom
Version: 0.0.1
Summary: My client for GigaChat
Home-page: https://github.com/averkij/gigachat-client
Author: Sergei Averkiev
Author-email: averoo@gmail.com
Project-URL: Bug Tracker, https://github.com/averkij/gigachat-client/issues
Classifier: Programming Language :: Python :: 3
Classifier: License :: OSI Approved :: GNU General Public License v3 (GPLv3)
Classifier: Operating System :: OS Independent
Requires-Python: >=3.6
License-File: LICENSE
